{
  "launchDate": "2026-05-04",
  "lastPost": {
    "date": "2026-05-06",
    "verseId": "sb-0005",
    "photoId": "pexels-35081866",
    "postId": "18068982581671254",
    "type": "reel",
    "carousel": false
  },
  "recentPhotos": [
    "mecca-silhouette-01",
    "mountain-light-01",
    "mushaf-tezhip-01",
    "rose-vase-01",
    "unsplash-jtOm3pGlXgo",
    "pexels-36114345",
    "pexels-35081866"
  ],
  "postedVerseIds": [
    "sb-0001",
    "sb-0002",
    "sb-0003",
    "sb-0004",
    "sb-0005"
  ],
  "usedVideoIds": [
    "pexels-36114345",
    "pexels-35081866"
  ]
}